PyResistorColorCode/Config.py
PyResistorColorCode/ConfigInstall.py
PyResistorColorCode/GuiTools.py
PyResistorColorCode/Help.py
PyResistorColorCode/Math.py
PyResistorColorCode/ResistorColourCode.py
PyResistorColorCode/ResistorDecoderApplication.py
PyResistorColorCode/ResistorWidget.py
PyResistorColorCode/__init__.py
PyResistorColorCode-1.0.0.data/data/share/PyResistorColorCode/icons/resistor.svg
PyResistorColorCode-1.0.0.data/data/share/applications/resistor-decoder.desktop
PyResistorColorCode-1.0.0.data/scripts/resistor-decoder
PyResistorColorCode-1.0.0.dist-info/DESCRIPTION.rst
PyResistorColorCode-1.0.0.dist-info/METADATA
PyResistorColorCode-1.0.0.dist-info/RECORD
PyResistorColorCode-1.0.0.dist-info/WHEEL
PyResistorColorCode-1.0.0.dist-info/metadata.json
PyResistorColorCode-1.0.0.dist-info/top_level.txt
