Metadata-Version: 2.0
Name: PyResistorColorCode
Version: 1.0.0
Summary: Python module providing some tools to manage IEC 60062 marking codes for resistors.
Home-page: https://github.com/FabriceSalvaire/PyResistorColorCode
Author: Fabrice Salvaire
Author-email: fabrice.salvaire@orange.fr
License: GPLv3
Keywords: resistor color colour code IEC 6006
Platform: any
Classifier: Topic :: Scientific/Engineering
Classifier: Intended Audience :: Education
Classifier: Development Status :: 5 - Production/Stable
Classifier: License :: OSI Approved :: GNU General Public License v3 (GPLv3)
Classifier: Operating System :: OS Independent
Classifier: Programming Language :: Python :: 3.0
Requires-Dist: PyQt5
